pysitk/__init__.py
pysitk/data_anonymizer.py
pysitk/definitions.py
pysitk/python_helper.py
pysitk/simple_itk_helper.py
pysitk/statistics_helper.py
pysitk/volume_splitter.py
PySiTK-0.2.2.dist-info/LICENSE
PySiTK-0.2.2.dist-info/METADATA
PySiTK-0.2.2.dist-info/WHEEL
PySiTK-0.2.2.dist-info/top_level.txt
PySiTK-0.2.2.dist-info/RECORD
