Metadata-Version: 2.1
Name: PySiTK
Version: 0.2.2
Summary: Python SimpleITK/WrapITK helper scripts
Home-page: https://github.com/gift-surg/PySiTK
Author: Michael Ebner
Author-email: michael.ebner.14@ucl.ac.uk
License: BSD-3-Clause
Keywords: development ITK SimpleITK
Platform: UNKNOWN
Classifier: Intended Audience :: Developers
Classifier: Intended Audience :: Healthcare Industry
Classifier: Intended Audience :: Science/Research
Classifier: License :: OSI Approved :: BSD License
Classifier: Topic :: Software Development :: Build Tools
Classifier: Topic :: Scientific/Engineering :: Medical Science Apps.
Classifier: Programming Language :: Python
Classifier: Programming Language :: Python :: 2
Classifier: Programming Language :: Python :: 3
Requires-Dist: pip (>=9.0.1)
Requires-Dist: setuptools (>=36.6.0)
Requires-Dist: nibabel (>=2.0.2)
Requires-Dist: matplotlib (>=1.4.3)
Requires-Dist: numpy (>=1.13.1)
Requires-Dist: cmake (>=0.8.0)
Requires-Dist: ninja (>=1.7.2)
Requires-Dist: SimpleITK (>=1.1.0)
Requires-Dist: scikit-image (>=0.13.1)
Requires-Dist: nose (>=1.3.7)
Requires-Dist: pandas (>=0.22)
Requires-Dist: seaborn (>=0.8.1)
